mcp_server_sqlite/__init__.py
mcp_server_sqlite/server.py
iflow_mcp_mcp_server_sqlite-0.6.2.dist-info/METADATA
iflow_mcp_mcp_server_sqlite-0.6.2.dist-info/WHEEL
iflow_mcp_mcp_server_sqlite-0.6.2.dist-info/entry_points.txt
iflow_mcp_mcp_server_sqlite-0.6.2.dist-info/RECORD
