Metadata-Version: 2.4
Name: iflow-mcp_mcp-server-sqlite
Version: 0.6.2
Summary: A simple SQLite MCP server
Requires-Python: >=3.10
Requires-Dist: mcp[cli]>=1.6.0
